classy/__init__.py
classy/version.py
classy/data/__init__.py
classy/data/data_drivers.py
classy/data/data_modules.py
classy/data/dataset/__init__.py
classy/data/dataset/base.py
classy/data/dataset/hf/__init__.py
classy/data/dataset/hf/base.py
classy/data/dataset/hf/classification.py
classy/data/dataset/hf/generation.py
classy/evaluation/__init__.py
classy/evaluation/base.py
classy/evaluation/generation.py
classy/evaluation/simple.py
classy/evaluation/span.py
classy/evaluation/squad.py
classy/optim/__init__.py
classy/optim/factories.py
classy/optim/optimizers/__init__.py
classy/optim/optimizers/radam.py
classy/pl_callbacks/__init__.py
classy/pl_callbacks/best_checkpoint.py
classy/pl_callbacks/prediction.py
classy/pl_modules/__init__.py
classy/pl_modules/base.py
classy/pl_modules/hf/__init__.py
classy/pl_modules/hf/classification.py
classy/pl_modules/hf/generation.py
classy/pl_modules/mixins/__init__.py
classy/pl_modules/mixins/prediction.py
classy/pl_modules/mixins/saving.py
classy/pl_modules/mixins/task.py
classy/pl_modules/mixins/task_serve.py
classy/pl_modules/mixins/task_ui.py
classy/scripts/__init__.py
classy/scripts/cli/__init__.py
classy/scripts/cli/demo.py
classy/scripts/cli/describe.py
classy/scripts/cli/download.py
classy/scripts/cli/evaluate.py
classy/scripts/cli/export.py
classy/scripts/cli/import_.py
classy/scripts/cli/predict.py
classy/scripts/cli/serve.py
classy/scripts/cli/train.py
classy/scripts/cli/upload.py
classy/scripts/cli/utils.py
classy/scripts/model/__init__.py
classy/scripts/model/demo.py
classy/scripts/model/describe.py
classy/scripts/model/download.py
classy/scripts/model/evaluate.py
classy/scripts/model/export.py
classy/scripts/model/import_.py
classy/scripts/model/predict.py
classy/scripts/model/serve.py
classy/scripts/model/train.py
classy/scripts/model/upload.py
classy/utils/__init__.py
classy/utils/commons.py
classy/utils/config.py
classy/utils/data.py
classy/utils/experiment.py
classy/utils/file.py
classy/utils/help_cli.py
classy_core-0.3.2.dist-info/LICENSE
classy_core-0.3.2.dist-info/METADATA
classy_core-0.3.2.dist-info/WHEEL
classy_core-0.3.2.dist-info/entry_points.txt
classy_core-0.3.2.dist-info/top_level.txt
classy_core-0.3.2.dist-info/RECORD
