Metadata-Version: 2.1
Name: classy-core
Version: 0.3.2
Summary: A powerful tool to train and use your classification models.
Home-page: https://github.com/sunglasses-ai/classy
Author: Classy Team @ Sunglasses AI
Author-email: classy@sunglasses.ai
License: Apache
Keywords: classy nn ml sunglassesai classification
Platform: UNKNOWN
Classifier: Development Status :: 3 - Alpha
Classifier: License :: OSI Approved :: Apache Software License
Classifier: Programming Language :: Python :: 3
Classifier: Operating System :: OS Independent
Classifier: Intended Audience :: Developers
Classifier: Intended Audience :: Education
Classifier: Intended Audience :: Science/Research
Classifier: Topic :: Text Processing :: Linguistic
Classifier: Topic :: Scientific/Engineering :: Artificial Intelligence
Requires-Python: >=3.8.0
License-File: LICENSE
Requires-Dist: torch (>=1.9)
Requires-Dist: pytorch-lightning (<1.6.0,>=1.5.0)
Requires-Dist: torchmetrics (<0.8.0,>=0.5.0)
Requires-Dist: transformers (<4.18,>=4.1)
Requires-Dist: hydra-core (==1.1.1)
Requires-Dist: argcomplete (==1.12.3)
Requires-Dist: wandb (>=0.12.0)
Requires-Dist: datasets (<1.19,>=1.12)
Requires-Dist: nltk (<4.0.0,>=3.4.5)
Requires-Dist: seqeval (==1.2.*)
Requires-Dist: rouge-score (==0.0.4)
Requires-Dist: sacrebleu (==2.0.0)
Requires-Dist: rich (>=11.0.0)
Requires-Dist: sentencepiece (==0.1.96)
Provides-Extra: all
Requires-Dist: plotly (==5.5.0) ; extra == 'all'
Requires-Dist: pdoc3 (==0.10.0) ; extra == 'all'
Requires-Dist: st-annotated-text (==2.0.0) ; extra == 'all'
Requires-Dist: streamlit (<1.5.0,>=1.4.0) ; extra == 'all'
Requires-Dist: fastapi (==0.68.1) ; extra == 'all'
Requires-Dist: uvicorn[standard] (==0.15.0) ; extra == 'all'
Provides-Extra: demo
Requires-Dist: streamlit (<1.5.0,>=1.4.0) ; extra == 'demo'
Requires-Dist: st-annotated-text (==2.0.0) ; extra == 'demo'
Provides-Extra: describe
Requires-Dist: plotly (==5.5.0) ; extra == 'describe'
Requires-Dist: streamlit (<1.5.0,>=1.4.0) ; extra == 'describe'
Requires-Dist: st-annotated-text (==2.0.0) ; extra == 'describe'
Provides-Extra: docs
Requires-Dist: pdoc3 (==0.10.0) ; extra == 'docs'
Provides-Extra: fastapi
Requires-Dist: fastapi (==0.68.1) ; extra == 'fastapi'
Provides-Extra: pdoc3
Requires-Dist: pdoc3 (==0.10.0) ; extra == 'pdoc3'
Provides-Extra: plotly
Requires-Dist: plotly (==5.5.0) ; extra == 'plotly'
Provides-Extra: serve
Requires-Dist: fastapi (==0.68.1) ; extra == 'serve'
Requires-Dist: uvicorn[standard] (==0.15.0) ; extra == 'serve'
Provides-Extra: st-annotated-text
Requires-Dist: st-annotated-text (==2.0.0) ; extra == 'st-annotated-text'
Provides-Extra: streamlit
Requires-Dist: streamlit (<1.5.0,>=1.4.0) ; extra == 'streamlit'
Provides-Extra: uvicorn_standard_
Requires-Dist: uvicorn[standard] (==0.15.0) ; extra == 'uvicorn_standard_'
